Metadata-Version: 2.1
Name: django-multiform-views
Version: 0.1.0a4
Summary: An expanded version of Django's FormViews to handle multiple forms with separate submission
Home-page: https://github.com/zagaran/django-multiform-views
Author: Zagaran, Inc.
Author-email: info@zagaran.com
License: MIT
Platform: UNKNOWN
Classifier: Development Status :: 3 - Alpha
Classifier: Environment :: Web Environment
Classifier: Intended Audience :: Developers
Classifier: License :: OSI Approved :: MIT License
Classifier: Operating System :: OS Independent
Classifier: Topic :: Software Development :: Testing
Classifier: Topic :: Software Development :: Libraries
Classifier: Programming Language :: Python
Classifier: Programming Language :: Python :: 3
Classifier: Programming Language :: Python :: 3.4
Classifier: Programming Language :: Python :: 3.5
Classifier: Programming Language :: Python :: 3.6
Classifier: Programming Language :: Python :: 3.7
